emotion_model/VERSION
emotion_model/__init__.py
emotion_model/emotion_pipeline.py
emotion_model/predict.py
emotion_model/train_pipeline.py
emotion_model/config/__init__.py
emotion_model/config/config.yaml
emotion_model/config/core.py
emotion_model/processing/__init__.py
emotion_model/processing/data_manager.py
emotion_model/trained_models/emotion_clf_output_v0.0.6.pkl
emotion_model/utils/__init__.py
emotion_model/utils/utils.py
emotion_model-0.0.6.dist-info/LICENSE.md
emotion_model-0.0.6.dist-info/METADATA
emotion_model-0.0.6.dist-info/WHEEL
emotion_model-0.0.6.dist-info/top_level.txt
emotion_model-0.0.6.dist-info/RECORD
